SPARQLStreamWrapper/KeyCaseInsensitiveDict.py
SPARQLStreamWrapper/OBDAUtils.py
SPARQLStreamWrapper/SPARQLExceptions.py
SPARQLStreamWrapper/Wrapper.py
SPARQLStreamWrapper/__init__.py
SPARQLStreamWrapper-0.1.dev0.dist-info/LICENSE.txt
SPARQLStreamWrapper-0.1.dev0.dist-info/METADATA
SPARQLStreamWrapper-0.1.dev0.dist-info/WHEEL
SPARQLStreamWrapper-0.1.dev0.dist-info/top_level.txt
SPARQLStreamWrapper-0.1.dev0.dist-info/RECORD
